{
  "id": "f93dff82-bd0d-4316-8854-dd0776cd63b3",
  "noticia": {
    "url": "https://www.giantfreakinrobot.com/ent/scifi/shivers-movie-review.html",
    "titulo": "Raunchy 70s Sci-Fi Horror From Master Director Is A Deadly Experiment",
    "data_publicacao": "2026-02-19T16:06:59Z",
    "fonte_id": "giant_freakin_robot_horror",
    "texto_resumido": "A fast-spreading parasitic infection that turns the entire world into one beautiful, mindless orgy may sound like a great idea … Continue reading \"Raunchy 70s Sci-Fi Horror From Master Director Is A Deadly Experiment\"",
    "coletado_em": "2026-04-13T23:08:22.007256Z",
    "raw_html": null
  },
  "categoria": "Notícia Geral do Gênero",
  "generos": [],
  "score": 0.007042253521126761,
  "aprovado_em": "2026-04-13T23:08:36.425106Z",
  "aprovado_por": "auto",
  "titulo_original": null,
  "autor": null,
  "editora": null,
  "data_prevista": null,
  "sinopse": null,
  "itens_relacionados": []
}